<StimSpec animation="false">
  <stimType>GA</stimType>
  <stimObjId>0</stimObjId>
  <xCenter>0.0</xCenter>
  <yCenter>0.0</yCenter>
  <size>1.0</size>
  <global__ori>0.0</global__ori>
  <doMorph>false</doMorph>
  <morphLengthWidthOnly>false</morphLengthWidthOnly>
  <ctrlPts>
    <double-array>
      <double>-1.1328909191273693</double>
      <double>-0.0229486972830637</double>
    </double-array>
    <double-array>
      <double>0.014581214653785812</double>
      <double>1.9628401650426</double>
    </double-array>
    <double-array>
      <double>0.0229486972830637</double>
      <double>-1.1328909191273693</double>
    </double-array>
    <double-array>
      <double>-2.666788819395774</double>
      <double>-3.96680276796548</double>
    </double-array>
    <double-array>
      <double>-4.689295563023772</double>
      <double>-4.769750295567329</double>
    </double-array>
    <double-array>
      <double>-3.8555519803220184</double>
      <double>-2.8252443671703626</double>
    </double-array>
    <double-array reference="../double-array"/>
    <double-array reference="../double-array[2]"/>
    <double-array reference="../double-array[3]"/>
  </ctrlPts>
  <foreColor>
    <double>1.0</double>
    <double>1.0</double>
    <double>1.0</double>
    <double>1.0</double>
  </foreColor>
  <backColor>
    <double>0.0</double>
    <double>0.0</double>
    <double>0.0</double>
    <double>1.0</double>
  </backColor>
  <fader>1.0</fader>
  <rng serialization="custom">
    <java.util.Random>
      <default>
        <seed>49814744432491</seed>
        <nextNextGaussian>0.0</nextNextGaussian>
        <haveNextNextGaussian>false</haveNextNextGaussian>
      </default>
    </java.util.Random>
  </rng>
  <growthFactor>0.0</growthFactor>
  <category>-1</category>
  <doRandom>false</doRandom>
  <morphLim>-1.0</morphLim>
  <morphLengthGain>-1.0</morphLengthGain>
  <morphWidthGain>-1.0</morphWidthGain>
  <morphBias>-1.0</morphBias>
  <limb>
    <nodeId>-1</nodeId>
    <length>5.532374805121058</length>
    <width>1.6024783788546073</width>
    <width2>1.6481242171636405</width2>
    <ori>226.16046803476527</ori>
    <curv>
      <double>1.7795707367729359</double>
      <double>1.8418375008805083</double>
      <double>0.6456601877657897</double>
      <double>0.4658760954987782</double>
      <double>1.4027595361662757</double>
      <double>0.9523201944446891</double>
      <double>0.7070785864296385</double>
      <double>1.1197636022782416</double>
    </curv>
    <xy>
      <double>0.0</double>
      <double>0.0</double>
    </xy>
    <isSmoother>true</isSmoother>
    <isSmoother2>true</isSmoother2>
  </limb>
</StimSpec>