<StimSpec animation="false">
  <stimType>GA</stimType>
  <stimObjId>0</stimObjId>
  <xCenter>0.0</xCenter>
  <yCenter>0.0</yCenter>
  <size>1.0</size>
  <global__ori>0.0</global__ori>
  <doMorph>false</doMorph>
  <morphLengthWidthOnly>false</morphLengthWidthOnly>
  <ctrlPts>
    <double-array>
      <double>-0.3195760409592747</double>
      <double>0.060723974477076614</double>
    </double-array>
    <double-array>
      <double>-0.25681144628656377</double>
      <double>0.19966003127241083</double>
    </double-array>
    <double-array>
      <double>2.143214165442361</double>
      <double>1.1742765529154526</double>
    </double-array>
    <double-array>
      <double>2.5787779487576805</double>
      <double>1.3230410121404828</double>
    </double-array>
    <double-array>
      <double>3.242170797232296</double>
      <double>0.6996720443194496</double>
    </double-array>
    <double-array>
      <double>2.357191354585905</double>
      <double>0.6449351126627096</double>
    </double-array>
    <double-array>
      <double>1.1514022385869844</double>
      <double>0.19136766539041655</double>
    </double-array>
    <double-array>
      <double>1.1587319119851518</double>
      <double>0.14031769142674688</double>
    </double-array>
    <double-array>
      <double>1.7848453943114457</double>
      <double>0.24429936249694878</double>
    </double-array>
    <double-array>
      <double>2.8439296151157736</double>
      <double>-0.9626001349578157</double>
    </double-array>
    <double-array>
      <double>1.701985185855135</double>
      <double>-0.5904250056026235</double>
    </double-array>
    <double-array>
      <double>0.47934875057650717</double>
      <double>-0.30292430788043095</double>
    </double-array>
    <double-array>
      <double>0.4078238528481778</double>
      <double>-0.39397724050021526</double>
    </double-array>
    <double-array>
      <double>2.2224286102028317</double>
      <double>-2.3173809084201715</double>
    </double-array>
    <double-array>
      <double>4.332898669255457</double>
      <double>-5.442606677004189</double>
    </double-array>
    <double-array>
      <double>0.5203607361071878</double>
      <double>-4.3948785883338655</double>
    </double-array>
    <double-array>
      <double>-0.28356963655672196</double>
      <double>-3.1982857069657613</double>
    </double-array>
    <double-array reference="../double-array"/>
    <double-array reference="../double-array[2]"/>
    <double-array reference="../double-array[3]"/>
  </ctrlPts>
  <foreColor>
    <double>1.0</double>
    <double>1.0</double>
    <double>1.0</double>
    <double>1.0</double>
  </foreColor>
  <backColor>
    <double>0.0</double>
    <double>0.0</double>
    <double>0.0</double>
    <double>1.0</double>
  </backColor>
  <fader>1.0</fader>
  <rng serialization="custom">
    <java.util.Random>
      <default>
        <seed>10895420112546</seed>
        <nextNextGaussian>0.0</nextNextGaussian>
        <haveNextNextGaussian>false</haveNextNextGaussian>
      </default>
    </java.util.Random>
  </rng>
  <growthFactor>0.0</growthFactor>
  <category>-1</category>
  <doRandom>false</doRandom>
  <morphLim>-1.0</morphLim>
  <morphLengthGain>-1.0</morphLengthGain>
  <morphWidthGain>-1.0</morphWidthGain>
  <morphBias>-1.0</morphBias>
  <limb>
    <nodeId>-1</nodeId>
    <length>4.25141667246179</length>
    <width>0.5081843740466427</width>
    <width2>2.65631708891514</width2>
    <ori>289.36751939828935</ori>
    <curv>
      <double>0.11487271743321137</double>
      <double>1.9685701578418937</double>
      <double>1.2837433019172384</double>
      <double>1.7039999990830141</double>
      <double>1.7187643233336953</double>
      <double>0.7277321695820922</double>
      <double>1.7468552651691178</double>
      <double>0.05069020077952735</double>
    </curv>
    <xy>
      <double>0.0</double>
      <double>0.0</double>
    </xy>
    <isSmoother>false</isSmoother>
    <isSmoother2>false</isSmoother2>
  </limb>
  <limb>
    <nodeId>0</nodeId>
    <length>2.1713973629741306</length>
    <width>0.8388269099430785</width>
    <width2>0.8388269099430785</width2>
    <ori>354.3310173753186</ori>
    <curv>
      <double>1.7970567855213275</double>
      <double>0.19296119174946424</double>
      <double>1.7278981591546432</double>
      <double>1.6323937981742056</double>
    </curv>
    <xy>
      <double>0.0</double>
      <double>0.0</double>
    </xy>
    <isSmoother>true</isSmoother>
    <isSmoother2>false</isSmoother2>
  </limb>
  <limb>
    <nodeId>0</nodeId>
    <length>2.712573105163279</length>
    <width>0.570954111853676</width>
    <width2>0.570954111853676</width2>
    <ori>382.01017571867965</ori>
    <curv>
      <double>0.9113249908886722</double>
      <double>1.9840275912136847</double>
      <double>0.6098364356791035</double>
      <double>1.9459235735268057</double>
    </curv>
    <xy>
      <double>0.0</double>
      <double>0.0</double>
    </xy>
    <isSmoother>false</isSmoother>
    <isSmoother2>false</isSmoother2>
  </limb>
</StimSpec>